charles_chou_technicalanalysis/target.py
charles_chou_technicalanalysis/technicalanalysis.py
charles_chou_technicalanalysis-0.1.0.dist-info/LICENSE
charles_chou_technicalanalysis-0.1.0.dist-info/METADATA
charles_chou_technicalanalysis-0.1.0.dist-info/WHEEL
charles_chou_technicalanalysis-0.1.0.dist-info/RECORD
