Metadata-Version: 2.1
Name: charles-chou-technicalanalysis
Version: 0.1.0
Summary: provide technical analysis of financial markets
License: MIT
Author: CC
Requires-Python: >=3.9,<4.0
Classifier: License :: OSI Approved :: MIT License
Classifier: Programming Language :: Python :: 3
Classifier: Programming Language :: Python :: 3.9
Classifier: Programming Language :: Python :: 3.10
Classifier: Programming Language :: Python :: 3.11
